{
    "set_name": "\n2008 Stormfront\n",
    "card_name": "Dusknoir LV.X   Holo",
    "population_report": [
        [
            "PSA10",
            "15"
        ],
        [
            "PSA9",
            "97"
        ],
        [
            "PSA8",
            "67"
        ],
        [
            "PSA7",
            "26"
        ],
        [
            "PSA6",
            "13"
        ],
        [
            "PSA5",
            "5"
        ],
        [
            "PSA4",
            "3"
        ],
        [
            "PSA3",
            "0"
        ],
        [
            "PSA2",
            "1"
        ],
        [
            "PSA1",
            "0"
        ]
    ],
    "pop_report_date": "Population Report as of Friday, November 10, 2023",
    "prices_data": [
        {
            "Date": "2023-02-27",
            "Grade": "8",
            "Price": "$30.09",
            "Sale Type": "Auction"
        },
        {
            "Date": "2023-01-21",
            "Grade": "8",
            "Price": "$42.69",
            "Sale Type": "Auction"
        },
        {
            "Date": "2023-01-09",
            "Grade": "8",
            "Price": "$38.51",
            "Sale Type": "Auction"
        },
        {
            "Date": "2022-12-26",
            "Grade": "6",
            "Price": "$25.01",
            "Sale Type": "Auction"
        },
        {
            "Date": "2022-12-11",
            "Grade": "8",
            "Price": "$39.00",
            "Sale Type": "Auction"
        },
        {
            "Date": "2022-12-11",
            "Grade": "9",
            "Price": "$90.00",
            "Sale Type": "Auction"
        },
        {
            "Date": "2022-12-11",
            "Grade": "9",
            "Price": "$86.00",
            "Sale Type": "Auction"
        },
        {
            "Date": "2022-06-07",
            "Grade": "9",
            "Price": "$33.00",
            "Sale Type": "Auction"
        },
        {
            "Date": "2022-01-24",
            "Grade": "8",
            "Price": "$47.00",
            "Sale Type": "Auction"
        },
        {
            "Date": "2022-01-24",
            "Grade": "8",
            "Price": "$60.00",
            "Sale Type": "Auction"
        },
        {
            "Date": "2021-12-06",
            "Grade": "10",
            "Price": "$780.00",
            "Sale Type": "Auction"
        },
        {
            "Date": "2021-11-30",
            "Grade": "8",
            "Price": "$51.00",
            "Sale Type": "Auction"
        },
        {
            "Date": "2021-11-21",
            "Grade": "8",
            "Price": "$62.00",
            "Sale Type": "Auction"
        },
        {
            "Date": "2021-09-30",
            "Grade": "9",
            "Price": "$125.00",
            "Sale Type": "Auction"
        },
        {
            "Date": "2021-08-25",
            "Grade": "9",
            "Price": "$152.50",
            "Sale Type": "Auction"
        },
        {
            "Date": "2021-08-23",
            "Grade": "9",
            "Price": "$148.50",
            "Sale Type": "Auction"
        },
        {
            "Date": "2021-05-26",
            "Grade": "5",
            "Price": "$20.50",
            "Sale Type": "Auction"
        },
        {
            "Date": "2021-02-15",
            "Grade": "5",
            "Price": "$50.00",
            "Sale Type": "Best Offer"
        },
        {
            "Date": "2020-12-29",
            "Grade": "10",
            "Price": "$1,050.00",
            "Sale Type": "Auction"
        },
        {
            "Date": "2020-12-28",
            "Grade": "9",
            "Price": "$100.00",
            "Sale Type": "Best Offer"
        },
        {
            "Date": "2020-12-23",
            "Grade": "9",
            "Price": "$99.95",
            "Sale Type": "Best Offer"
        },
        {
            "Date": "2020-12-20",
            "Grade": "9",
            "Price": "$76.00",
            "Sale Type": "Auction"
        },
        {
            "Date": "2020-10-17",
            "Grade": "9",
            "Price": "$56.82",
            "Sale Type": "Best Offer"
        },
        {
            "Date": "2020-10-17",
            "Grade": "9",
            "Price": "$65.00",
            "Sale Type": "Best Offer"
        },
        {
            "Date": "2020-09-04",
            "Grade": "9",
            "Price": "$31.00",
            "Sale Type": "Auction"
        },
        {
            "Date": "2020-09-03",
            "Grade": "5",
            "Price": "$182.00",
            "Sale Type": "Auction"
        },
        {
            "Date": "2020-08-16",
            "Grade": "5",
            "Price": "$100.00",
            "Sale Type": "Auction"
        },
        {
            "Date": "2020-08-16",
            "Grade": "5",
            "Price": "$20.00",
            "Sale Type": "Auction"
        },
        {
            "Date": "2020-08-10",
            "Grade": "9",
            "Price": "$399.99",
            "Sale Type": "Buy It Now"
        },
        {
            "Date": "2020-06-29",
            "Grade": "9",
            "Price": "$49.99",
            "Sale Type": "Best Offer"
        },
        {
            "Date": "2020-06-06",
            "Grade": "8",
            "Price": "$29.99",
            "Sale Type": "Buy It Now"
        },
        {
            "Date": "2020-06-06",
            "Grade": "10",
            "Price": "$149.95",
            "Sale Type": "Buy It Now"
        },
        {
            "Date": "2020-05-19",
            "Grade": "8",
            "Price": "$21.00",
            "Sale Type": "Buy It Now"
        },
        {
            "Date": "2020-05-09",
            "Grade": "10",
            "Price": "$149.95",
            "Sale Type": "Buy It Now"
        },
        {
            "Date": "2020-04-30",
            "Grade": "9",
            "Price": "$20.50",
            "Sale Type": "Auction"
        },
        {
            "Date": "2020-04-29",
            "Grade": "9",
            "Price": "$16.22",
            "Sale Type": "Auction"
        },
        {
            "Date": "2020-04-14",
            "Grade": "9",
            "Price": "$24.60",
            "Sale Type": "Auction"
        },
        {
            "Date": "2020-03-25",
            "Grade": "9",
            "Price": "$20.00",
            "Sale Type": "Auction"
        },
        {
            "Date": "2020-03-14",
            "Grade": "9",
            "Price": "$22.50",
            "Sale Type": "Auction"
        },
        {
            "Date": "2020-01-17",
            "Grade": "9",
            "Price": "$16.51",
            "Sale Type": "Auction"
        },
        {
            "Date": "2020-01-15",
            "Grade": "9",
            "Price": "$18.17",
            "Sale Type": "Auction"
        },
        {
            "Date": "2020-01-05",
            "Grade": "9",
            "Price": "$26.01",
            "Sale Type": "Auction"
        },
        {
            "Date": "2019-12-23",
            "Grade": "9",
            "Price": "$12.28",
            "Sale Type": "Auction"
        },
        {
            "Date": "2019-12-16",
            "Grade": "9",
            "Price": "$44.99",
            "Sale Type": "Best Offer"
        },
        {
            "Date": "2019-12-10",
            "Grade": "9",
            "Price": "$24.49",
            "Sale Type": "Auction"
        },
        {
            "Date": "2019-11-26",
            "Grade": "9",
            "Price": "$16.50",
            "Sale Type": "Auction"
        },
        {
            "Date": "2019-10-05",
            "Grade": "8",
            "Price": "$20.00",
            "Sale Type": "Auction"
        },
        {
            "Date": "2019-09-25",
            "Grade": "8",
            "Price": "$9.50",
            "Sale Type": "Auction"
        },
        {
            "Date": "2019-07-04",
            "Grade": "10",
            "Price": "$39.00",
            "Sale Type": "Best Offer"
        },
        {
            "Date": "2019-06-16",
            "Grade": "5",
            "Price": "$3.25",
            "Sale Type": "Auction"
        },
        {
            "Date": "2019-06-13",
            "Grade": "9",
            "Price": "$23.50",
            "Sale Type": "Auction"
        },
        {
            "Date": "2019-03-28",
            "Grade": "9",
            "Price": "$18.50",
            "Sale Type": "Auction"
        },
        {
            "Date": "2019-03-21",
            "Grade": "9",
            "Price": "$22.51",
            "Sale Type": "Auction"
        },
        {
            "Date": "2019-03-15",
            "Grade": "9",
            "Price": "$11.50",
            "Sale Type": "Auction"
        },
        {
            "Date": "2019-03-13",
            "Grade": "9",
            "Price": "$11.00",
            "Sale Type": "Auction"
        },
        {
            "Date": "2019-03-07",
            "Grade": "9",
            "Price": "$13.05",
            "Sale Type": "Auction"
        },
        {
            "Date": "2019-03-04",
            "Grade": "9",
            "Price": "$31.00",
            "Sale Type": "Auction"
        },
        {
            "Date": "2019-02-25",
            "Grade": "9",
            "Price": "$12.50",
            "Sale Type": "Auction"
        },
        {
            "Date": "2019-02-15",
            "Grade": "9",
            "Price": "$12.50",
            "Sale Type": "Auction"
        },
        {
            "Date": "2019-01-30",
            "Grade": "9",
            "Price": "$12.50",
            "Sale Type": "Auction"
        },
        {
            "Date": "2019-01-23",
            "Grade": "9",
            "Price": "$14.50",
            "Sale Type": "Auction"
        },
        {
            "Date": "2019-01-17",
            "Grade": "9",
            "Price": "$12.50",
            "Sale Type": "Auction"
        },
        {
            "Date": "2018-12-30",
            "Grade": "9",
            "Price": "$14.99",
            "Sale Type": "Auction"
        },
        {
            "Date": "2018-07-10",
            "Grade": "9",
            "Price": "$12.50",
            "Sale Type": "Auction"
        },
        {
            "Date": "2018-06-19",
            "Grade": "10",
            "Price": "$36.00",
            "Sale Type": "Auction"
        },
        {
            "Date": "2018-06-18",
            "Grade": "9",
            "Price": "$13.27",
            "Sale Type": "Auction"
        },
        {
            "Date": "2018-06-13",
            "Grade": "9",
            "Price": "$15.50",
            "Sale Type": "Auction"
        },
        {
            "Date": "2018-06-03",
            "Grade": "9",
            "Price": "$14.00",
            "Sale Type": "Auction"
        },
        {
            "Date": "2018-06-02",
            "Grade": "10",
            "Price": "$41.00",
            "Sale Type": "Auction"
        },
        {
            "Date": "2018-05-29",
            "Grade": "9",
            "Price": "$1.25",
            "Sale Type": "Auction"
        },
        {
            "Date": "2018-05-28",
            "Grade": "10",
            "Price": "$32.77",
            "Sale Type": "Auction"
        },
        {
            "Date": "2018-05-24",
            "Grade": "9",
            "Price": "$12.50",
            "Sale Type": "Auction"
        },
        {
            "Date": "2018-05-21",
            "Grade": "10",
            "Price": "$24.50",
            "Sale Type": "Auction"
        },
        {
            "Date": "2018-05-19",
            "Grade": "9",
            "Price": "$23.27",
            "Sale Type": "Auction"
        },
        {
            "Date": "2018-05-16",
            "Grade": "10",
            "Price": "$31.00",
            "Sale Type": "Auction"
        },
        {
            "Date": "2018-03-29",
            "Grade": "10",
            "Price": "$35.00",
            "Sale Type": "Auction"
        },
        {
            "Date": "2018-03-13",
            "Grade": "9",
            "Price": "$5.58",
            "Sale Type": "Auction"
        },
        {
            "Date": "2017-12-17",
            "Grade": "9",
            "Price": "$11.50",
            "Sale Type": "Auction"
        }
    ]
}