{
    "set_name": "\n2003 EX Dragon\n",
    "card_name": "Vibrava Reverse Foil  ",
    "population_report": [
        [
            "PSA10",
            "3"
        ],
        [
            "PSA9",
            "12"
        ],
        [
            "PSA8",
            "15"
        ],
        [
            "PSA7",
            "7"
        ],
        [
            "PSA6",
            "2"
        ],
        [
            "PSA5",
            "0"
        ],
        [
            "PSA4",
            "1"
        ],
        [
            "PSA3",
            "0"
        ],
        [
            "PSA2",
            "0"
        ],
        [
            "PSA1",
            "0"
        ]
    ],
    "pop_report_date": "Population Report as of Friday, November 10, 2023",
    "prices_data": [
        {
            "Date": "2023-02-20",
            "Grade": "7",
            "Price": "$15.42",
            "Sale Type": "Auction"
        },
        {
            "Date": "2020-05-30",
            "Grade": "9",
            "Price": "$24.99",
            "Sale Type": "Best Offer"
        },
        {
            "Date": "2020-04-20",
            "Grade": "8",
            "Price": "$9.98",
            "Sale Type": "Auction"
        },
        {
            "Date": "2019-10-24",
            "Grade": "10",
            "Price": "$15.50",
            "Sale Type": "Auction"
        }
    ]
}