{
    "set_name": "\n2000 Gym Challenge\n",
    "card_name": "Rocket's Mewtwo Holo-1st Edition  ",
    "population_report": [
        [
            "PSA10",
            "260"
        ],
        [
            "PSA9",
            "693"
        ],
        [
            "PSA8",
            "247"
        ],
        [
            "PSA7",
            "97"
        ],
        [
            "PSA6",
            "41"
        ],
        [
            "PSA5",
            "36"
        ],
        [
            "PSA4",
            "16"
        ],
        [
            "PSA3",
            "6"
        ],
        [
            "PSA2",
            "4"
        ],
        [
            "PSA1",
            "3"
        ]
    ],
    "pop_report_date": "Population Report as of Friday, November 10, 2023",
    "prices_data": [
        {
            "Date": "2023-04-07",
            "Grade": "8",
            "Price": "$184.50",
            "Sale Type": "Auction"
        },
        {
            "Date": "2023-04-03",
            "Grade": "10",
            "Price": "$1,075.00",
            "Sale Type": "Auction"
        },
        {
            "Date": "2023-03-26",
            "Grade": "9",
            "Price": "$359.51",
            "Sale Type": "Auction"
        },
        {
            "Date": "2023-03-12",
            "Grade": "9",
            "Price": "$349.99",
            "Sale Type": "Auction"
        },
        {
            "Date": "2023-03-06",
            "Grade": "10",
            "Price": "$960.00",
            "Sale Type": "Auction"
        },
        {
            "Date": "2023-02-27",
            "Grade": "9",
            "Price": "$320.00",
            "Sale Type": "Auction"
        },
        {
            "Date": "2023-02-13",
            "Grade": "9",
            "Price": "$339.99",
            "Sale Type": "Auction"
        },
        {
            "Date": "2023-02-06",
            "Grade": "9",
            "Price": "$327.00",
            "Sale Type": "Auction"
        },
        {
            "Date": "2023-02-05",
            "Grade": "9",
            "Price": "$324.34",
            "Sale Type": "Auction"
        },
        {
            "Date": "2023-01-28",
            "Grade": "9",
            "Price": "$315.00",
            "Sale Type": "Auction"
        },
        {
            "Date": "2023-01-23",
            "Grade": "9",
            "Price": "$461.00",
            "Sale Type": "Auction"
        },
        {
            "Date": "2023-01-23",
            "Grade": "8",
            "Price": "$202.50",
            "Sale Type": "Auction"
        },
        {
            "Date": "2023-01-09",
            "Grade": "7",
            "Price": "$117.50",
            "Sale Type": "Auction"
        },
        {
            "Date": "2023-01-07",
            "Grade": "10",
            "Price": "$1,100.00",
            "Sale Type": "Auction"
        },
        {
            "Date": "2022-12-26",
            "Grade": "8",
            "Price": "$190.00",
            "Sale Type": "Auction"
        },
        {
            "Date": "2022-12-13",
            "Grade": "5",
            "Price": "$100.00",
            "Sale Type": "Auction"
        },
        {
            "Date": "2022-12-12",
            "Grade": "10",
            "Price": "$1,045.00",
            "Sale Type": "Auction"
        },
        {
            "Date": "2022-12-09",
            "Grade": "8",
            "Price": "$176.50",
            "Sale Type": "Auction"
        },
        {
            "Date": "2022-01-07",
            "Grade": "10",
            "Price": "$1,345.00",
            "Sale Type": "Auction"
        },
        {
            "Date": "2021-12-13",
            "Grade": "9",
            "Price": "$305.50",
            "Sale Type": "Auction"
        },
        {
            "Date": "2021-12-05",
            "Grade": "9",
            "Price": "$370.00",
            "Sale Type": "Auction"
        },
        {
            "Date": "2021-11-27",
            "Grade": "10",
            "Price": "$1,699.99",
            "Sale Type": "Auction"
        },
        {
            "Date": "2021-11-20",
            "Grade": "9",
            "Price": "$353.00",
            "Sale Type": "Auction"
        },
        {
            "Date": "2021-11-14",
            "Grade": "9",
            "Price": "$330.00",
            "Sale Type": "Auction"
        },
        {
            "Date": "2021-11-12",
            "Grade": "8",
            "Price": "$210.50",
            "Sale Type": "Auction"
        },
        {
            "Date": "2021-11-07",
            "Grade": "9",
            "Price": "$296.78",
            "Sale Type": "Auction"
        },
        {
            "Date": "2021-10-25",
            "Grade": "9",
            "Price": "$340.00",
            "Sale Type": "Auction"
        },
        {
            "Date": "2021-10-23",
            "Grade": "8",
            "Price": "$205.00",
            "Sale Type": "Auction"
        },
        {
            "Date": "2021-09-26",
            "Grade": "6",
            "Price": "$80.00",
            "Sale Type": "Auction"
        },
        {
            "Date": "2021-09-26",
            "Grade": "8",
            "Price": "$255.00",
            "Sale Type": "Auction"
        },
        {
            "Date": "2021-09-19",
            "Grade": "9",
            "Price": "$300.00",
            "Sale Type": "Auction"
        },
        {
            "Date": "2021-09-12",
            "Grade": "9",
            "Price": "$310.00",
            "Sale Type": "Auction"
        },
        {
            "Date": "2021-08-24",
            "Grade": "10",
            "Price": "$1,125.00",
            "Sale Type": "Auction"
        },
        {
            "Date": "2021-08-18",
            "Grade": "9",
            "Price": "$460.00",
            "Sale Type": "Auction"
        },
        {
            "Date": "2021-08-01",
            "Grade": "7",
            "Price": "$192.50",
            "Sale Type": "Auction"
        },
        {
            "Date": "2021-07-30",
            "Grade": "9",
            "Price": "$510.00",
            "Sale Type": "Auction"
        },
        {
            "Date": "2021-07-28",
            "Grade": "8",
            "Price": "$273.92",
            "Sale Type": "Auction"
        },
        {
            "Date": "2021-06-10",
            "Grade": "10",
            "Price": "$1,075.00",
            "Sale Type": "Auction"
        },
        {
            "Date": "2021-05-29",
            "Grade": "9",
            "Price": "$405.00",
            "Sale Type": "Auction"
        },
        {
            "Date": "2021-05-29",
            "Grade": "9",
            "Price": "$444.00",
            "Sale Type": "Auction"
        },
        {
            "Date": "2021-05-20",
            "Grade": "9",
            "Price": "$500.00",
            "Sale Type": "Auction"
        },
        {
            "Date": "2021-05-18",
            "Grade": "8",
            "Price": "$305.00",
            "Sale Type": "Auction"
        },
        {
            "Date": "2021-05-15",
            "Grade": "8",
            "Price": "$300.00",
            "Sale Type": "Auction"
        },
        {
            "Date": "2021-04-28",
            "Grade": "10",
            "Price": "$1,325.00",
            "Sale Type": "Auction"
        },
        {
            "Date": "2021-04-28",
            "Grade": "9",
            "Price": "$610.00",
            "Sale Type": "Auction"
        },
        {
            "Date": "2021-04-28",
            "Grade": "10",
            "Price": "$1,275.00",
            "Sale Type": "Auction"
        },
        {
            "Date": "2021-04-27",
            "Grade": "9",
            "Price": "$455.00",
            "Sale Type": "Auction"
        },
        {
            "Date": "2021-04-17",
            "Grade": "9",
            "Price": "$500.00",
            "Sale Type": "Best Offer"
        },
        {
            "Date": "2021-04-16",
            "Grade": "8",
            "Price": "$370.00",
            "Sale Type": "Best Offer"
        },
        {
            "Date": "2021-04-11",
            "Grade": "5",
            "Price": "$170.49",
            "Sale Type": "Auction"
        },
        {
            "Date": "2021-04-06",
            "Grade": "9",
            "Price": "$620.00",
            "Sale Type": "Auction"
        },
        {
            "Date": "2021-04-03",
            "Grade": "9",
            "Price": "$1,034.04",
            "Sale Type": "Best Offer"
        },
        {
            "Date": "2021-04-03",
            "Grade": "8",
            "Price": "$374.00",
            "Sale Type": "Auction"
        },
        {
            "Date": "2021-04-02",
            "Grade": "10",
            "Price": "$1,600.00",
            "Sale Type": "Auction"
        },
        {
            "Date": "2021-04-02",
            "Grade": "10",
            "Price": "$1,500.00",
            "Sale Type": "Best Offer"
        },
        {
            "Date": "2021-04-01",
            "Grade": "9",
            "Price": "$510.00",
            "Sale Type": "Auction"
        },
        {
            "Date": "2021-04-01",
            "Grade": "9",
            "Price": "$510.00",
            "Sale Type": "Auction"
        },
        {
            "Date": "2021-03-30",
            "Grade": "8",
            "Price": "$380.00",
            "Sale Type": "Auction"
        },
        {
            "Date": "2021-03-29",
            "Grade": "7",
            "Price": "$295.00",
            "Sale Type": "Auction"
        },
        {
            "Date": "2021-03-29",
            "Grade": "8",
            "Price": "$420.00",
            "Sale Type": "Auction"
        },
        {
            "Date": "2021-03-29",
            "Grade": "9",
            "Price": "$532.00",
            "Sale Type": "Auction"
        },
        {
            "Date": "2021-03-29",
            "Grade": "9",
            "Price": "$732.00",
            "Sale Type": "Auction"
        },
        {
            "Date": "2021-03-26",
            "Grade": "10",
            "Price": "$2,399.00",
            "Sale Type": "Best Offer"
        },
        {
            "Date": "2021-03-23",
            "Grade": "9",
            "Price": "$779.25",
            "Sale Type": "Auction"
        },
        {
            "Date": "2021-03-08",
            "Grade": "9",
            "Price": "$550.00",
            "Sale Type": "Best Offer"
        },
        {
            "Date": "2021-02-28",
            "Grade": "8",
            "Price": "$450.00",
            "Sale Type": "Best Offer"
        },
        {
            "Date": "2021-02-28",
            "Grade": "9",
            "Price": "$570.00",
            "Sale Type": "Auction"
        },
        {
            "Date": "2021-02-28",
            "Grade": "9",
            "Price": "$780.00",
            "Sale Type": "Auction"
        },
        {
            "Date": "2021-02-24",
            "Grade": "9",
            "Price": "$500.00",
            "Sale Type": "Best Offer"
        },
        {
            "Date": "2021-02-20",
            "Grade": "9",
            "Price": "$564.00",
            "Sale Type": "Auction"
        },
        {
            "Date": "2021-02-16",
            "Grade": "9",
            "Price": "$700.00",
            "Sale Type": "Best Offer"
        },
        {
            "Date": "2021-02-10",
            "Grade": "9",
            "Price": "$415.00",
            "Sale Type": "Auction"
        },
        {
            "Date": "2021-02-08",
            "Grade": "9",
            "Price": "$500.00",
            "Sale Type": "Auction"
        },
        {
            "Date": "2021-02-07",
            "Grade": "8",
            "Price": "$472.27",
            "Sale Type": "Best Offer"
        },
        {
            "Date": "2021-02-04",
            "Grade": "9",
            "Price": "$522.00",
            "Sale Type": "Auction"
        },
        {
            "Date": "2021-02-02",
            "Grade": "9",
            "Price": "$511.00",
            "Sale Type": "Auction"
        },
        {
            "Date": "2021-02-02",
            "Grade": "10",
            "Price": "$1,500.00",
            "Sale Type": "Best Offer"
        },
        {
            "Date": "2021-02-01",
            "Grade": "9",
            "Price": "$611.00",
            "Sale Type": "Auction"
        },
        {
            "Date": "2021-01-30",
            "Grade": "7",
            "Price": "$260.00",
            "Sale Type": "Best Offer"
        },
        {
            "Date": "2021-01-28",
            "Grade": "9",
            "Price": "$404.00",
            "Sale Type": "Auction"
        },
        {
            "Date": "2021-01-28",
            "Grade": "9",
            "Price": "$375.00",
            "Sale Type": "Auction"
        },
        {
            "Date": "2021-01-28",
            "Grade": "10",
            "Price": "$1,547.00",
            "Sale Type": "Auction"
        },
        {
            "Date": "2021-01-28",
            "Grade": "9",
            "Price": "$385.00",
            "Sale Type": "Auction"
        },
        {
            "Date": "2021-01-27",
            "Grade": "9",
            "Price": "$450.00",
            "Sale Type": "Best Offer"
        },
        {
            "Date": "2021-01-22",
            "Grade": "10",
            "Price": "$1,750.00",
            "Sale Type": "Best Offer"
        },
        {
            "Date": "2021-01-14",
            "Grade": "9",
            "Price": "$550.00",
            "Sale Type": "Best Offer"
        },
        {
            "Date": "2021-01-04",
            "Grade": "10",
            "Price": "$1,375.00",
            "Sale Type": "Auction"
        },
        {
            "Date": "2021-01-03",
            "Grade": "6",
            "Price": "$233.00",
            "Sale Type": "Best Offer"
        },
        {
            "Date": "2021-01-03",
            "Grade": "10",
            "Price": "$1,500.00",
            "Sale Type": "Best Offer"
        },
        {
            "Date": "2021-01-03",
            "Grade": "9",
            "Price": "$600.00",
            "Sale Type": "Auction"
        },
        {
            "Date": "2021-01-01",
            "Grade": "10",
            "Price": "$2,000.00",
            "Sale Type": "Best Offer"
        },
        {
            "Date": "2020-12-26",
            "Grade": "10",
            "Price": "$1,000.00",
            "Sale Type": "Auction"
        },
        {
            "Date": "2020-12-21",
            "Grade": "8",
            "Price": "$355.00",
            "Sale Type": "Auction"
        },
        {
            "Date": "2020-12-20",
            "Grade": "10",
            "Price": "$1,500.00",
            "Sale Type": "Auction"
        },
        {
            "Date": "2020-12-19",
            "Grade": "7",
            "Price": "$222.50",
            "Sale Type": "Auction"
        },
        {
            "Date": "2020-12-14",
            "Grade": "9",
            "Price": "$449.00",
            "Sale Type": "Auction"
        },
        {
            "Date": "2020-12-12",
            "Grade": "9",
            "Price": "$453.00",
            "Sale Type": "Auction"
        },
        {
            "Date": "2020-12-07",
            "Grade": "9",
            "Price": "$600.00",
            "Sale Type": "Best Offer"
        },
        {
            "Date": "2020-12-06",
            "Grade": "10",
            "Price": "$1,630.00",
            "Sale Type": "Auction"
        },
        {
            "Date": "2020-12-01",
            "Grade": "8",
            "Price": "$315.00",
            "Sale Type": "Auction"
        },
        {
            "Date": "2020-12-01",
            "Grade": "10",
            "Price": "$1,450.00",
            "Sale Type": "Auction"
        },
        {
            "Date": "2020-11-29",
            "Grade": "9",
            "Price": "$456.11",
            "Sale Type": "Auction"
        },
        {
            "Date": "2020-11-23",
            "Grade": "9",
            "Price": "$580.00",
            "Sale Type": "Best Offer"
        },
        {
            "Date": "2020-11-23",
            "Grade": "9",
            "Price": "$601.00",
            "Sale Type": "Auction"
        },
        {
            "Date": "2020-11-22",
            "Grade": "8",
            "Price": "$377.00",
            "Sale Type": "Auction"
        },
        {
            "Date": "2020-11-20",
            "Grade": "9",
            "Price": "$500.00",
            "Sale Type": "Auction"
        },
        {
            "Date": "2020-11-18",
            "Grade": "9",
            "Price": "$640.00",
            "Sale Type": "Auction"
        },
        {
            "Date": "2020-11-15",
            "Grade": "9",
            "Price": "$610.00",
            "Sale Type": "Auction"
        },
        {
            "Date": "2020-11-15",
            "Grade": "9",
            "Price": "$575.00",
            "Sale Type": "Best Offer"
        },
        {
            "Date": "2020-11-11",
            "Grade": "8",
            "Price": "$760.00",
            "Sale Type": "Auction"
        },
        {
            "Date": "2020-11-09",
            "Grade": "10",
            "Price": "$1,700.00",
            "Sale Type": "Best Offer"
        },
        {
            "Date": "2020-11-08",
            "Grade": "9",
            "Price": "$660.00",
            "Sale Type": "Auction"
        },
        {
            "Date": "2020-10-30",
            "Grade": "10",
            "Price": "$1,999.99",
            "Sale Type": "Best Offer"
        },
        {
            "Date": "2020-10-30",
            "Grade": "8",
            "Price": "$600.00",
            "Sale Type": "Best Offer"
        },
        {
            "Date": "2020-10-28",
            "Grade": "10",
            "Price": "$1,728.00",
            "Sale Type": "Auction"
        },
        {
            "Date": "2020-10-28",
            "Grade": "10",
            "Price": "$1,675.00",
            "Sale Type": "Auction"
        },
        {
            "Date": "2020-10-21",
            "Grade": "9",
            "Price": "$550.00",
            "Sale Type": "Best Offer"
        },
        {
            "Date": "2020-10-19",
            "Grade": "10",
            "Price": "$1,641.92",
            "Sale Type": "Auction"
        },
        {
            "Date": "2020-10-14",
            "Grade": "9",
            "Price": "$425.00",
            "Sale Type": "Best Offer"
        },
        {
            "Date": "2020-10-13",
            "Grade": "7",
            "Price": "$185.50",
            "Sale Type": "Auction"
        },
        {
            "Date": "2020-10-12",
            "Grade": "9",
            "Price": "$350.00",
            "Sale Type": "Best Offer"
        },
        {
            "Date": "2020-09-30",
            "Grade": "9",
            "Price": "$325.00",
            "Sale Type": "Best Offer"
        },
        {
            "Date": "2020-09-29",
            "Grade": "10",
            "Price": "$1,100.00",
            "Sale Type": "Auction"
        },
        {
            "Date": "2020-09-29",
            "Grade": "8",
            "Price": "$183.00",
            "Sale Type": "Auction"
        },
        {
            "Date": "2020-09-29",
            "Grade": "10",
            "Price": "$1,080.00",
            "Sale Type": "Best Offer"
        },
        {
            "Date": "2020-09-19",
            "Grade": "10",
            "Price": "$1,100.00",
            "Sale Type": "Best Offer"
        },
        {
            "Date": "2020-09-05",
            "Grade": "10",
            "Price": "$950.00",
            "Sale Type": "Auction"
        },
        {
            "Date": "2020-08-28",
            "Grade": "9",
            "Price": "$295.00",
            "Sale Type": "Auction"
        },
        {
            "Date": "2020-08-28",
            "Grade": "9",
            "Price": "$300.00",
            "Sale Type": "Best Offer"
        },
        {
            "Date": "2020-08-21",
            "Grade": "9",
            "Price": "$300.00",
            "Sale Type": "Best Offer"
        },
        {
            "Date": "2020-08-14",
            "Grade": "7",
            "Price": "$133.50",
            "Sale Type": "Auction"
        },
        {
            "Date": "2020-08-06",
            "Grade": "9",
            "Price": "$340.00",
            "Sale Type": "Auction"
        },
        {
            "Date": "2020-07-29",
            "Grade": "8",
            "Price": "$175.00",
            "Sale Type": "Auction"
        },
        {
            "Date": "2020-07-25",
            "Grade": "7",
            "Price": "$102.50",
            "Sale Type": "Auction"
        },
        {
            "Date": "2020-07-25",
            "Grade": "9",
            "Price": "$282.00",
            "Sale Type": "Best Offer"
        },
        {
            "Date": "2020-07-17",
            "Grade": "9",
            "Price": "$260.00",
            "Sale Type": "Auction"
        },
        {
            "Date": "2020-07-16",
            "Grade": "9",
            "Price": "$301.00",
            "Sale Type": "Auction"
        },
        {
            "Date": "2020-07-16",
            "Grade": "9",
            "Price": "$306.00",
            "Sale Type": "Buy It Now"
        },
        {
            "Date": "2020-07-11",
            "Grade": "9",
            "Price": "$315.00",
            "Sale Type": "Buy It Now"
        },
        {
            "Date": "2020-07-10",
            "Grade": "10",
            "Price": "$800.00",
            "Sale Type": "Buy It Now"
        },
        {
            "Date": "2020-07-06",
            "Grade": "9",
            "Price": "$233.51",
            "Sale Type": "Auction"
        },
        {
            "Date": "2020-07-05",
            "Grade": "10",
            "Price": "$850.00",
            "Sale Type": "Buy It Now"
        },
        {
            "Date": "2020-07-04",
            "Grade": "8",
            "Price": "$175.00",
            "Sale Type": "Buy It Now"
        },
        {
            "Date": "2020-06-29",
            "Grade": "9",
            "Price": "$320.00",
            "Sale Type": "Auction"
        },
        {
            "Date": "2020-06-29",
            "Grade": "10",
            "Price": "$800.00",
            "Sale Type": "Buy It Now"
        },
        {
            "Date": "2020-06-08",
            "Grade": "9",
            "Price": "$258.00",
            "Sale Type": "Auction"
        },
        {
            "Date": "2020-06-03",
            "Grade": "9",
            "Price": "$340.00",
            "Sale Type": "Auction"
        },
        {
            "Date": "2020-06-02",
            "Grade": "10",
            "Price": "$850.00",
            "Sale Type": "Auction"
        },
        {
            "Date": "2020-05-26",
            "Grade": "9",
            "Price": "$259.99",
            "Sale Type": "Best Offer"
        },
        {
            "Date": "2020-05-20",
            "Grade": "9",
            "Price": "$280.00",
            "Sale Type": "Buy It Now"
        },
        {
            "Date": "2020-05-15",
            "Grade": "10",
            "Price": "$805.00",
            "Sale Type": "Auction"
        },
        {
            "Date": "2020-05-10",
            "Grade": "9",
            "Price": "$280.00",
            "Sale Type": "Auction"
        },
        {
            "Date": "2020-05-08",
            "Grade": "10",
            "Price": "$555.00",
            "Sale Type": "Buy It Now"
        },
        {
            "Date": "2020-05-08",
            "Grade": "9",
            "Price": "$198.50",
            "Sale Type": "Auction"
        },
        {
            "Date": "2020-05-02",
            "Grade": "9",
            "Price": "$220.50",
            "Sale Type": "Auction"
        },
        {
            "Date": "2020-04-26",
            "Grade": "9",
            "Price": "$182.50",
            "Sale Type": "Auction"
        },
        {
            "Date": "2020-04-25",
            "Grade": "9",
            "Price": "$223.10",
            "Sale Type": "Buy It Now"
        },
        {
            "Date": "2020-04-24",
            "Grade": "8",
            "Price": "$132.50",
            "Sale Type": "Auction"
        },
        {
            "Date": "2020-04-12",
            "Grade": "10",
            "Price": "$599.99",
            "Sale Type": "Buy It Now"
        },
        {
            "Date": "2020-04-11",
            "Grade": "10",
            "Price": "$599.98",
            "Sale Type": "Auction"
        },
        {
            "Date": "2020-04-07",
            "Grade": "9",
            "Price": "$160.00",
            "Sale Type": "Auction"
        },
        {
            "Date": "2020-04-04",
            "Grade": "9",
            "Price": "$132.50",
            "Sale Type": "Auction"
        },
        {
            "Date": "2020-04-04",
            "Grade": "9",
            "Price": "$180.00",
            "Sale Type": "Best Offer"
        },
        {
            "Date": "2020-03-25",
            "Grade": "9",
            "Price": "$160.00",
            "Sale Type": "Auction"
        },
        {
            "Date": "2020-02-27",
            "Grade": "8",
            "Price": "$105.00",
            "Sale Type": "Buy It Now"
        },
        {
            "Date": "2020-02-16",
            "Grade": "9",
            "Price": "$150.00",
            "Sale Type": "Best Offer"
        },
        {
            "Date": "2020-01-28",
            "Grade": "9",
            "Price": "$122.50",
            "Sale Type": "Auction"
        },
        {
            "Date": "2020-01-27",
            "Grade": "10",
            "Price": "$208.25",
            "Sale Type": "Auction"
        },
        {
            "Date": "2019-11-18",
            "Grade": "9",
            "Price": "$98.00",
            "Sale Type": "Auction"
        },
        {
            "Date": "2019-10-28",
            "Grade": "10",
            "Price": "$215.50",
            "Sale Type": "Auction"
        },
        {
            "Date": "2019-07-08",
            "Grade": "9",
            "Price": "$99.99",
            "Sale Type": "Best Offer"
        },
        {
            "Date": "2019-06-30",
            "Grade": "10",
            "Price": "$187.50",
            "Sale Type": "Auction"
        },
        {
            "Date": "2019-06-19",
            "Grade": "10",
            "Price": "$147.50",
            "Sale Type": "Auction"
        },
        {
            "Date": "2019-05-28",
            "Grade": "10",
            "Price": "$175.00",
            "Sale Type": "Best Offer"
        },
        {
            "Date": "2019-05-20",
            "Grade": "9",
            "Price": "$69.95",
            "Sale Type": "Buy It Now"
        },
        {
            "Date": "2019-05-20",
            "Grade": "10",
            "Price": "$180.00",
            "Sale Type": "Buy It Now"
        },
        {
            "Date": "2019-04-30",
            "Grade": "9",
            "Price": "$57.95",
            "Sale Type": "Best Offer"
        },
        {
            "Date": "2019-04-29",
            "Grade": "9",
            "Price": "$48.00",
            "Sale Type": "Auction"
        },
        {
            "Date": "2019-03-27",
            "Grade": "10",
            "Price": "$152.50",
            "Sale Type": "Auction"
        },
        {
            "Date": "2019-03-21",
            "Grade": "9",
            "Price": "$62.99",
            "Sale Type": "Buy It Now"
        },
        {
            "Date": "2019-03-14",
            "Grade": "9",
            "Price": "$59.99",
            "Sale Type": "Buy It Now"
        },
        {
            "Date": "2019-03-14",
            "Grade": "10",
            "Price": "$190.00",
            "Sale Type": "Auction"
        },
        {
            "Date": "2019-03-10",
            "Grade": "9",
            "Price": "$61.00",
            "Sale Type": "Auction"
        },
        {
            "Date": "2019-02-27",
            "Grade": "9",
            "Price": "$64.87",
            "Sale Type": "Auction"
        },
        {
            "Date": "2019-02-26",
            "Grade": "9",
            "Price": "$43.01",
            "Sale Type": "Auction"
        },
        {
            "Date": "2019-02-26",
            "Grade": "10",
            "Price": "$175.00",
            "Sale Type": "Auction"
        },
        {
            "Date": "2019-02-07",
            "Grade": "10",
            "Price": "$133.50",
            "Sale Type": "Auction"
        },
        {
            "Date": "2019-02-01",
            "Grade": "10",
            "Price": "$173.99",
            "Sale Type": "Buy It Now"
        },
        {
            "Date": "2019-01-18",
            "Grade": "9",
            "Price": "$65.00",
            "Sale Type": "Best Offer"
        },
        {
            "Date": "2019-01-14",
            "Grade": "10",
            "Price": "$107.50",
            "Sale Type": "Auction"
        },
        {
            "Date": "2019-01-11",
            "Grade": "9",
            "Price": "$54.00",
            "Sale Type": "Auction"
        },
        {
            "Date": "2019-01-10",
            "Grade": "10",
            "Price": "$140.50",
            "Sale Type": "Auction"
        },
        {
            "Date": "2018-12-26",
            "Grade": "9",
            "Price": "$50.51",
            "Sale Type": "Auction"
        },
        {
            "Date": "2018-12-20",
            "Grade": "9",
            "Price": "$59.99",
            "Sale Type": "Best Offer"
        },
        {
            "Date": "2018-12-06",
            "Grade": "10",
            "Price": "$130.00",
            "Sale Type": "Best Offer"
        },
        {
            "Date": "2018-10-27",
            "Grade": "10",
            "Price": "$77.00",
            "Sale Type": "Auction"
        },
        {
            "Date": "2018-09-07",
            "Grade": "9",
            "Price": "$62.00",
            "Sale Type": "Buy It Now"
        },
        {
            "Date": "2018-09-04",
            "Grade": "10",
            "Price": "$175.00",
            "Sale Type": "Best Offer"
        },
        {
            "Date": "2018-09-03",
            "Grade": "9",
            "Price": "$65.00",
            "Sale Type": "Auction"
        },
        {
            "Date": "2018-08-29",
            "Grade": "10",
            "Price": "$167.50",
            "Sale Type": "Auction"
        },
        {
            "Date": "2018-08-29",
            "Grade": "10",
            "Price": "$203.50",
            "Sale Type": "Auction"
        },
        {
            "Date": "2018-08-29",
            "Grade": "10",
            "Price": "$142.00",
            "Sale Type": "Best Offer"
        },
        {
            "Date": "2018-08-24",
            "Grade": "9",
            "Price": "$59.00",
            "Sale Type": "Auction"
        },
        {
            "Date": "2018-08-17",
            "Grade": "9",
            "Price": "$48.00",
            "Sale Type": "Auction"
        },
        {
            "Date": "2018-08-12",
            "Grade": "10",
            "Price": "$127.50",
            "Sale Type": "Auction"
        },
        {
            "Date": "2018-07-29",
            "Grade": "9",
            "Price": "$81.00",
            "Sale Type": "Auction"
        },
        {
            "Date": "2018-07-29",
            "Grade": "10",
            "Price": "$157.50",
            "Sale Type": "Auction"
        },
        {
            "Date": "2018-07-15",
            "Grade": "9",
            "Price": "$55.00",
            "Sale Type": "Best Offer"
        },
        {
            "Date": "2018-07-12",
            "Grade": "9",
            "Price": "$55.00",
            "Sale Type": "Buy It Now"
        },
        {
            "Date": "2018-07-11",
            "Grade": "10",
            "Price": "$155.00",
            "Sale Type": "Buy It Now"
        },
        {
            "Date": "2018-06-26",
            "Grade": "10",
            "Price": "$175.52",
            "Sale Type": "Auction"
        },
        {
            "Date": "2018-06-26",
            "Grade": "10",
            "Price": "$158.50",
            "Sale Type": "Auction"
        },
        {
            "Date": "2018-06-25",
            "Grade": "10",
            "Price": "$181.81",
            "Sale Type": "Auction"
        },
        {
            "Date": "2018-06-24",
            "Grade": "8",
            "Price": "$43.00",
            "Sale Type": "Auction"
        },
        {
            "Date": "2018-06-17",
            "Grade": "10",
            "Price": "$229.99",
            "Sale Type": "Buy It Now"
        },
        {
            "Date": "2018-06-04",
            "Grade": "10",
            "Price": "$189.27",
            "Sale Type": "Auction"
        },
        {
            "Date": "2018-05-22",
            "Grade": "9",
            "Price": "$42.76",
            "Sale Type": "Auction"
        },
        {
            "Date": "2018-05-21",
            "Grade": "10",
            "Price": "$145.00",
            "Sale Type": "Best Offer"
        },
        {
            "Date": "2018-05-21",
            "Grade": "9",
            "Price": "$60.00",
            "Sale Type": "Best Offer"
        },
        {
            "Date": "2018-05-11",
            "Grade": "9",
            "Price": "$62.00",
            "Sale Type": "Auction"
        },
        {
            "Date": "2018-05-01",
            "Grade": "10",
            "Price": "$205.00",
            "Sale Type": "Best Offer"
        },
        {
            "Date": "2018-04-29",
            "Grade": "10",
            "Price": "$167.50",
            "Sale Type": "Auction"
        },
        {
            "Date": "2018-04-10",
            "Grade": "10",
            "Price": "$185.00",
            "Sale Type": "Best Offer"
        },
        {
            "Date": "2018-04-08",
            "Grade": "9",
            "Price": "$60.00",
            "Sale Type": "Best Offer"
        },
        {
            "Date": "2018-03-31",
            "Grade": "9",
            "Price": "$65.00",
            "Sale Type": "Best Offer"
        },
        {
            "Date": "2018-03-28",
            "Grade": "10",
            "Price": "$181.00",
            "Sale Type": "Auction"
        },
        {
            "Date": "2018-03-24",
            "Grade": "9",
            "Price": "$74.95",
            "Sale Type": "Buy It Now"
        },
        {
            "Date": "2018-03-18",
            "Grade": "9",
            "Price": "$70.00",
            "Sale Type": "Best Offer"
        },
        {
            "Date": "2018-03-11",
            "Grade": "9",
            "Price": "$65.00",
            "Sale Type": "Best Offer"
        },
        {
            "Date": "2018-03-09",
            "Grade": "10",
            "Price": "$200.00",
            "Sale Type": "Best Offer"
        },
        {
            "Date": "2018-02-28",
            "Grade": "10",
            "Price": "$160.00",
            "Sale Type": "Buy It Now"
        },
        {
            "Date": "2018-02-18",
            "Grade": "8",
            "Price": "$24.50",
            "Sale Type": "Auction"
        },
        {
            "Date": "2018-02-16",
            "Grade": "9",
            "Price": "$60.00",
            "Sale Type": "Best Offer"
        },
        {
            "Date": "2018-02-10",
            "Grade": "9",
            "Price": "$61.00",
            "Sale Type": "Auction"
        },
        {
            "Date": "2018-02-04",
            "Grade": "10",
            "Price": "$159.50",
            "Sale Type": "Auction"
        },
        {
            "Date": "2018-02-03",
            "Grade": "10",
            "Price": "$127.50",
            "Sale Type": "Auction"
        },
        {
            "Date": "2018-01-24",
            "Grade": "9",
            "Price": "$69.99",
            "Sale Type": "Buy It Now"
        },
        {
            "Date": "2018-01-21",
            "Grade": "10",
            "Price": "$200.03",
            "Sale Type": "Auction"
        },
        {
            "Date": "2018-01-21",
            "Grade": "7",
            "Price": "$16.46",
            "Sale Type": "Auction"
        },
        {
            "Date": "2018-01-12",
            "Grade": "9",
            "Price": "$40.00",
            "Sale Type": "Auction"
        },
        {
            "Date": "2018-01-10",
            "Grade": "10",
            "Price": "$180.00",
            "Sale Type": "Best Offer"
        },
        {
            "Date": "2018-01-05",
            "Grade": "9",
            "Price": "$65.00",
            "Sale Type": "Best Offer"
        },
        {
            "Date": "2017-12-15",
            "Grade": "9",
            "Price": "$65.00",
            "Sale Type": "Best Offer"
        },
        {
            "Date": "2017-12-10",
            "Grade": "9",
            "Price": "$51.00",
            "Sale Type": "Auction"
        },
        {
            "Date": "2017-11-29",
            "Grade": "10",
            "Price": "$142.50",
            "Sale Type": "Auction"
        },
        {
            "Date": "2017-11-28",
            "Grade": "9",
            "Price": "$70.00",
            "Sale Type": "Best Offer"
        },
        {
            "Date": "2017-11-25",
            "Grade": "10",
            "Price": "$183.00",
            "Sale Type": "Best Offer"
        },
        {
            "Date": "2017-11-23",
            "Grade": "9",
            "Price": "$85.00",
            "Sale Type": "Buy It Now"
        },
        {
            "Date": "2017-11-22",
            "Grade": "9",
            "Price": "$85.00",
            "Sale Type": "Buy It Now"
        },
        {
            "Date": "2017-11-19",
            "Grade": "10",
            "Price": "$200.00",
            "Sale Type": "Best Offer"
        },
        {
            "Date": "2017-11-18",
            "Grade": "9",
            "Price": "$95.00",
            "Sale Type": "Best Offer"
        },
        {
            "Date": "2017-11-09",
            "Grade": "9",
            "Price": "$47.00",
            "Sale Type": "Auction"
        },
        {
            "Date": "2017-11-09",
            "Grade": "10",
            "Price": "$157.50",
            "Sale Type": "Auction"
        },
        {
            "Date": "2017-11-04",
            "Grade": "9",
            "Price": "$89.99",
            "Sale Type": "Best Offer"
        },
        {
            "Date": "2017-10-30",
            "Grade": "9",
            "Price": "$59.00",
            "Sale Type": "Best Offer"
        },
        {
            "Date": "2017-10-24",
            "Grade": "9",
            "Price": "$79.99",
            "Sale Type": "Buy It Now"
        },
        {
            "Date": "2017-10-23",
            "Grade": "10",
            "Price": "$175.00",
            "Sale Type": "Best Offer"
        },
        {
            "Date": "2017-10-15",
            "Grade": "9",
            "Price": "$56.00",
            "Sale Type": "Auction"
        },
        {
            "Date": "2017-10-11",
            "Grade": "9",
            "Price": "$70.00",
            "Sale Type": "Best Offer"
        },
        {
            "Date": "2017-10-03",
            "Grade": "10",
            "Price": "$190.00",
            "Sale Type": "Best Offer"
        },
        {
            "Date": "2017-10-01",
            "Grade": "9",
            "Price": "$55.00",
            "Sale Type": "Auction"
        },
        {
            "Date": "2017-10-01",
            "Grade": "10",
            "Price": "$224.72",
            "Sale Type": "Auction"
        },
        {
            "Date": "2017-09-27",
            "Grade": "9",
            "Price": "$59.00",
            "Sale Type": "Auction"
        },
        {
            "Date": "2017-09-21",
            "Grade": "10",
            "Price": "$91.83",
            "Sale Type": "Auction"
        },
        {
            "Date": "2017-09-07",
            "Grade": "9",
            "Price": "$55.00",
            "Sale Type": "Best Offer"
        },
        {
            "Date": "2017-08-30",
            "Grade": "9",
            "Price": "$51.00",
            "Sale Type": "Auction"
        },
        {
            "Date": "2017-08-09",
            "Grade": "8",
            "Price": "$37.00",
            "Sale Type": "Auction"
        },
        {
            "Date": "2017-08-06",
            "Grade": "9",
            "Price": "$79.99",
            "Sale Type": "Buy It Now"
        },
        {
            "Date": "2017-07-16",
            "Grade": "10",
            "Price": "$155.00",
            "Sale Type": "Auction"
        },
        {
            "Date": "2017-07-05",
            "Grade": "9",
            "Price": "$79.00",
            "Sale Type": "Best Offer"
        },
        {
            "Date": "2017-07-05",
            "Grade": "10",
            "Price": "$225.00",
            "Sale Type": "Best Offer"
        },
        {
            "Date": "2017-06-30",
            "Grade": "9",
            "Price": "$50.00",
            "Sale Type": "Auction"
        },
        {
            "Date": "2017-06-25",
            "Grade": "10",
            "Price": "$130.59",
            "Sale Type": "Auction"
        },
        {
            "Date": "2017-06-14",
            "Grade": "10",
            "Price": "$132.00",
            "Sale Type": "Best Offer"
        },
        {
            "Date": "2017-04-30",
            "Grade": "9",
            "Price": "$33.00",
            "Sale Type": "Auction"
        },
        {
            "Date": "2017-04-02",
            "Grade": "9",
            "Price": "$89.00",
            "Sale Type": "Auction"
        },
        {
            "Date": "2017-02-22",
            "Grade": "9",
            "Price": "$56.00",
            "Sale Type": "Auction"
        },
        {
            "Date": "2017-01-16",
            "Grade": "10",
            "Price": "$75.01",
            "Sale Type": "Auction"
        },
        {
            "Date": "2016-12-05",
            "Grade": "9",
            "Price": "$35.00",
            "Sale Type": "Auction"
        },
        {
            "Date": "2016-11-27",
            "Grade": "10",
            "Price": "$87.50",
            "Sale Type": "Auction"
        }
    ]
}