{
    "set_name": "\n2019 Unified Minds\n",
    "card_name": "Full Art/Dragonite GX Secret  ",
    "population_report": [
        [
            "PSA10",
            "231"
        ],
        [
            "PSA9",
            "174"
        ],
        [
            "PSA8",
            "27"
        ],
        [
            "PSA7",
            "8"
        ],
        [
            "PSA6",
            "0"
        ],
        [
            "PSA5",
            "1"
        ],
        [
            "PSA4",
            "1"
        ],
        [
            "PSA3",
            "0"
        ],
        [
            "PSA2",
            "0"
        ],
        [
            "PSA1",
            "0"
        ]
    ],
    "pop_report_date": "Population Report as of Wednesday, November 9, 2022",
    "prices_data": [
        {
            "Date": "2023-10-30",
            "Grade": "10",
            "Price": "$91.00",
            "Sale Type": "Auction"
        },
        {
            "Date": "2023-10-24",
            "Grade": "10",
            "Price": "$113.57",
            "Sale Type": "Auction"
        },
        {
            "Date": "2023-10-15",
            "Grade": "10",
            "Price": "$124.50",
            "Sale Type": "Auction"
        },
        {
            "Date": "2023-10-12",
            "Grade": "10",
            "Price": "$122.50",
            "Sale Type": "Auction"
        },
        {
            "Date": "2023-09-28",
            "Grade": "9",
            "Price": "$38.00",
            "Sale Type": "Auction"
        },
        {
            "Date": "2023-09-24",
            "Grade": "10",
            "Price": "$100.00",
            "Sale Type": "Auction"
        },
        {
            "Date": "2023-09-11",
            "Grade": "10",
            "Price": "$115.01",
            "Sale Type": "Auction"
        },
        {
            "Date": "2023-09-03",
            "Grade": "9",
            "Price": "$35.00",
            "Sale Type": "Auction"
        },
        {
            "Date": "2023-08-27",
            "Grade": "9",
            "Price": "$45.00",
            "Sale Type": "Auction"
        },
        {
            "Date": "2023-08-14",
            "Grade": "10",
            "Price": "$122.50",
            "Sale Type": "Auction"
        },
        {
            "Date": "2023-08-07",
            "Grade": "9",
            "Price": "$41.01",
            "Sale Type": "Auction"
        },
        {
            "Date": "2023-07-01",
            "Grade": "9",
            "Price": "$43.27",
            "Sale Type": "Auction"
        },
        {
            "Date": "2023-04-03",
            "Grade": "10",
            "Price": "$172.50",
            "Sale Type": "Auction"
        },
        {
            "Date": "2023-03-22",
            "Grade": "10",
            "Price": "$155.50",
            "Sale Type": "Auction"
        },
        {
            "Date": "2023-03-21",
            "Grade": "9",
            "Price": "$61.14",
            "Sale Type": "Auction"
        },
        {
            "Date": "2023-03-13",
            "Grade": "9",
            "Price": "$41.00",
            "Sale Type": "Auction"
        },
        {
            "Date": "2023-03-04",
            "Grade": "9",
            "Price": "$50.00",
            "Sale Type": "Auction"
        },
        {
            "Date": "2023-02-25",
            "Grade": "9",
            "Price": "$61.00",
            "Sale Type": "Auction"
        },
        {
            "Date": "2023-02-03",
            "Grade": "10",
            "Price": "$160.00",
            "Sale Type": "Auction"
        },
        {
            "Date": "2023-01-30",
            "Grade": "9",
            "Price": "$40.00",
            "Sale Type": "Auction"
        },
        {
            "Date": "2022-12-24",
            "Grade": "9",
            "Price": "$61.00",
            "Sale Type": "Auction"
        },
        {
            "Date": "2022-12-23",
            "Grade": "9",
            "Price": "$37.00",
            "Sale Type": "Auction"
        },
        {
            "Date": "2022-12-09",
            "Grade": "9",
            "Price": "$41.00",
            "Sale Type": "Auction"
        },
        {
            "Date": "2022-10-27",
            "Grade": "9",
            "Price": "$30.00",
            "Sale Type": "Auction"
        },
        {
            "Date": "2022-05-08",
            "Grade": "10",
            "Price": "$143.50",
            "Sale Type": "Auction"
        },
        {
            "Date": "2022-02-19",
            "Grade": "9",
            "Price": "$76.00",
            "Sale Type": "Auction"
        },
        {
            "Date": "2022-01-29",
            "Grade": "10",
            "Price": "$181.19",
            "Sale Type": "Auction"
        },
        {
            "Date": "2022-01-25",
            "Grade": "9",
            "Price": "$97.00",
            "Sale Type": "Auction"
        },
        {
            "Date": "2021-12-27",
            "Grade": "9",
            "Price": "$58.00",
            "Sale Type": "Auction"
        },
        {
            "Date": "2021-12-26",
            "Grade": "9",
            "Price": "$56.00",
            "Sale Type": "Auction"
        },
        {
            "Date": "2021-12-21",
            "Grade": "10",
            "Price": "$265.00",
            "Sale Type": "Auction"
        },
        {
            "Date": "2021-10-20",
            "Grade": "10",
            "Price": "$202.50",
            "Sale Type": "Auction"
        },
        {
            "Date": "2021-10-14",
            "Grade": "10",
            "Price": "$305.00",
            "Sale Type": "Auction"
        },
        {
            "Date": "2021-10-13",
            "Grade": "9",
            "Price": "$75.00",
            "Sale Type": "Auction"
        },
        {
            "Date": "2021-09-06",
            "Grade": "8",
            "Price": "$75.01",
            "Sale Type": "Auction"
        },
        {
            "Date": "2021-08-30",
            "Grade": "8",
            "Price": "$50.00",
            "Sale Type": "Auction"
        },
        {
            "Date": "2021-08-17",
            "Grade": "9",
            "Price": "$91.00",
            "Sale Type": "Auction"
        },
        {
            "Date": "2021-08-08",
            "Grade": "10",
            "Price": "$212.50",
            "Sale Type": "Auction"
        },
        {
            "Date": "2021-06-19",
            "Grade": "9",
            "Price": "$80.00",
            "Sale Type": "Auction"
        },
        {
            "Date": "2021-06-11",
            "Grade": "9",
            "Price": "$159.99",
            "Sale Type": "Auction"
        },
        {
            "Date": "2021-05-24",
            "Grade": "9",
            "Price": "$107.50",
            "Sale Type": "Auction"
        },
        {
            "Date": "2021-05-02",
            "Grade": "10",
            "Price": "$251.99",
            "Sale Type": "Auction"
        },
        {
            "Date": "2021-04-21",
            "Grade": "10",
            "Price": "$290.00",
            "Sale Type": "Auction"
        },
        {
            "Date": "2021-03-24",
            "Grade": "9",
            "Price": "$42.00",
            "Sale Type": "Auction"
        },
        {
            "Date": "2021-03-15",
            "Grade": "9",
            "Price": "$150.00",
            "Sale Type": "Best Offer"
        },
        {
            "Date": "2021-03-02",
            "Grade": "10",
            "Price": "$399.95",
            "Sale Type": "Best Offer"
        },
        {
            "Date": "2021-02-11",
            "Grade": "10",
            "Price": "$285.00",
            "Sale Type": "Auction"
        },
        {
            "Date": "2021-02-02",
            "Grade": "10",
            "Price": "$325.00",
            "Sale Type": "Best Offer"
        },
        {
            "Date": "2021-01-01",
            "Grade": "10",
            "Price": "$290.00",
            "Sale Type": "Best Offer"
        },
        {
            "Date": "2020-12-08",
            "Grade": "9",
            "Price": "$128.00",
            "Sale Type": "Best Offer"
        },
        {
            "Date": "2020-11-05",
            "Grade": "10",
            "Price": "$215.00",
            "Sale Type": "Best Offer"
        },
        {
            "Date": "2020-10-25",
            "Grade": "10",
            "Price": "$188.22",
            "Sale Type": "Auction"
        },
        {
            "Date": "2020-05-22",
            "Grade": "9",
            "Price": "$44.95",
            "Sale Type": "Buy It Now"
        },
        {
            "Date": "2020-05-12",
            "Grade": "10",
            "Price": "$76.00",
            "Sale Type": "Auction"
        },
        {
            "Date": "2020-05-04",
            "Grade": "10",
            "Price": "$90.00",
            "Sale Type": "Buy It Now"
        },
        {
            "Date": "2020-04-21",
            "Grade": "10",
            "Price": "$61.00",
            "Sale Type": "Auction"
        },
        {
            "Date": "2020-04-15",
            "Grade": "9",
            "Price": "$38.00",
            "Sale Type": "Auction"
        },
        {
            "Date": "2020-04-12",
            "Grade": "10",
            "Price": "$55.99",
            "Sale Type": "Buy It Now"
        },
        {
            "Date": "2020-04-09",
            "Grade": "10",
            "Price": "$52.00",
            "Sale Type": "Best Offer"
        },
        {
            "Date": "2020-04-07",
            "Grade": "10",
            "Price": "$79.00",
            "Sale Type": "Auction"
        },
        {
            "Date": "2020-04-03",
            "Grade": "9",
            "Price": "$40.00",
            "Sale Type": "Buy It Now"
        },
        {
            "Date": "2020-03-28",
            "Grade": "10",
            "Price": "$59.00",
            "Sale Type": "Auction"
        },
        {
            "Date": "2020-02-23",
            "Grade": "10",
            "Price": "$46.99",
            "Sale Type": "Auction"
        },
        {
            "Date": "2020-02-22",
            "Grade": "9",
            "Price": "$42.00",
            "Sale Type": "Auction"
        },
        {
            "Date": "2020-02-13",
            "Grade": "9",
            "Price": "$17.50",
            "Sale Type": "Auction"
        },
        {
            "Date": "2020-01-31",
            "Grade": "10",
            "Price": "$38.00",
            "Sale Type": "Auction"
        },
        {
            "Date": "2020-01-24",
            "Grade": "10",
            "Price": "$89.99",
            "Sale Type": "Best Offer"
        },
        {
            "Date": "2020-01-16",
            "Grade": "10",
            "Price": "$54.99",
            "Sale Type": "Buy It Now"
        },
        {
            "Date": "2019-12-22",
            "Grade": "10",
            "Price": "$55.99",
            "Sale Type": "Best Offer"
        },
        {
            "Date": "2019-12-14",
            "Grade": "10",
            "Price": "$28.03",
            "Sale Type": "Auction"
        },
        {
            "Date": "2019-11-26",
            "Grade": "10",
            "Price": "$39.13",
            "Sale Type": "Auction"
        },
        {
            "Date": "2019-10-31",
            "Grade": "10",
            "Price": "$44.00",
            "Sale Type": "Auction"
        }
    ]
}